rayter_generator/__init__.py
rayter_generator/env.py
rayter_generator/games.py
rayter_generator/global_chart.py
rayter_generator/main.py
rayter_generator/players.py
rayter_generator/render.py
rayter_generator/settings.py
rayter_generator/static/css/main.css
rayter_generator/static/css/normalize.css
rayter_generator/static/img/arrow_down.gif
rayter_generator/static/img/arrow_up.gif
rayter_generator/static/js/charts.js
rayter_generator/templates/base.html
rayter_generator/templates/game.html
rayter_generator/templates/index.html
rayter_generator/templates/player.html
rayter_generator-1.0.16.dist-info/METADATA
rayter_generator-1.0.16.dist-info/WHEEL
rayter_generator-1.0.16.dist-info/entry_points.txt
rayter_generator-1.0.16.dist-info/top_level.txt
rayter_generator-1.0.16.dist-info/RECORD
