Metadata-Version: 2.1
Name: rayter_generator
Version: 1.0.16
Requires-Dist: rayter
Requires-Dist: jinja2
Requires-Dist: tomli
Requires-Dist: py-avataaars
Requires-Dist: requests
Requires-Dist: puremagic
Requires-Dist: numpy
